googlemap/__init__.py
googlemap-0.1.0.dist-info/METADATA
googlemap-0.1.0.dist-info/WHEEL
googlemap-0.1.0.dist-info/top_level.txt
googlemap-0.1.0.dist-info/RECORD
